AUTHORS
CHANGELOG
COPYING
INSTALL
MANIFEST.in
README
TODO
setup.py
PyDAV.egg-info/PKG-INFO
PyDAV.egg-info/SOURCES.txt
PyDAV.egg-info/top_level.txt
WebDAV/App_Common.py
WebDAV/__init__.py
WebDAV/client.py
WebDAV/common.py
WebDAV/httplib0.py
example/simple.py
tests/__init__.py
tests/test_http.py
tests/test_https.py
