Metadata-Version: 1.0
Name: PyDAV
Version: 0.21
Summary: Python WebDAV client library
Home-page: https://shuya.ath.cx/~neocool/code/pydav/
Author: Boris Buegling
Author-email: boris@icculus.org
License: ZPL 2.0
Download-URL: https://shuya.ath.cx/~neocool/code/pydav/pydav-latest.tar.bz2
Keywords: webdav
Platform: UNKNOWN
